hytils/__init__.py
hytils/extra.py
hytils/p_print.py
hytils/p_print.pyi
hytils/path.py
hytils/time_conversions.py
hytils-0.2.0.dist-info/licenses/LICENSE
hytils-0.2.0.dist-info/METADATA
hytils-0.2.0.dist-info/WHEEL
hytils-0.2.0.dist-info/top_level.txt
hytils-0.2.0.dist-info/RECORD
