Metadata-Version: 2.4
Name: hytils
Version: 0.2.0
Summary: Shared utilities: paths, formatting, and helpers
Author: Jep Etau
License-Expression: MIT
Project-URL: Homepage, https://github.com/herlegon/hytils
Classifier: Development Status :: 3 - Alpha
Classifier: Intended Audience :: Developers
Classifier: Operating System :: OS Independent
Classifier: Programming Language :: Python :: 3.12
Requires-Python: >=3.12
License-File: LICENSE
Dynamic: license-file
